ahk/__init__.py
ahk/_constants.py
ahk/_hotkey.py
ahk/_types.py
ahk/_utils.py
ahk/directives.py
ahk/exceptions.py
ahk/extensions.py
ahk/keys.py
ahk/message.py
ahk/py.typed
ahk/_async/__init__.py
ahk/_async/engine.py
ahk/_async/transport.py
ahk/_async/window.py
ahk/_sync/__init__.py
ahk/_sync/engine.py
ahk/_sync/transport.py
ahk/_sync/window.py
ahk/templates/daemon-v2.ahk
ahk/templates/daemon.ahk
ahk/templates/hotkeys-v2.ahk
ahk/templates/hotkeys.ahk
ahk-1.8.4.dist-info/licenses/LICENSE
ahk-1.8.4.dist-info/METADATA
ahk-1.8.4.dist-info/WHEEL
ahk-1.8.4.dist-info/top_level.txt
ahk-1.8.4.dist-info/RECORD
