Metadata-Version: 2.4
Name: ahk
Version: 1.8.4
Summary: A Python wrapper for AHK
Home-page: https://github.com/spyoungtech/ahk
Author: Spencer Young
Author-email: spencer.young@spyoung.com
Project-URL: Documentation, https://ahk.readthedocs.io/en/latest/
Project-URL: Funding, https://github.com/sponsors/spyoungtech/
Project-URL: Source, https://github.com/spyoungtech/ahk
Project-URL: Tracker, https://github.com/spyoungtech/ahk/issues
Keywords: ahk,autohotkey,windows,mouse,keyboard,automation,pyautogui
Classifier: Intended Audience :: Developers
Classifier: Topic :: Desktop Environment
Classifier: Programming Language :: Python
Classifier: Environment :: Win32 (MS Windows)
Classifier: License :: OSI Approved :: MIT License
Classifier: Operating System :: Microsoft :: Windows
Classifier: Programming Language :: Python :: 3 :: Only
Classifier: Programming Language :: Python :: 3.8
Classifier: Programming Language :: Python :: 3.9
Classifier: Programming Language :: Python :: 3.10
Classifier: Programming Language :: Python :: 3.11
Classifier: Programming Language :: Python :: 3.12
Classifier: Programming Language :: Python :: 3.13
Classifier: Typing :: Typed
Requires-Python: >=3.8.0
License-File: LICENSE
Requires-Dist: typing_extensions; python_version < "3.11"
Requires-Dist: jinja2>=3.0
Provides-Extra: binary
Requires-Dist: ahk-binary==2023.9.0; extra == "binary"
Dynamic: license-file
